Lab6/JKFF.v
module JKFF(
	output reg Q,
	output reg Qbar,
	input J,
	input K,
	input RST,
	input CLK
);
initial Q=0;
always@(posedge CLK)
if(RST==1)
	begin
	Q<=0;
	Qbar<=1;
	end
else
	begin
	case({J,K})
	2'b00: begin Q<=Q; Qbar<=Qbar; end
	2'b01: begin Q<=0; Qbar<=1; end
	2'b10: begin Q<=1; Qbar<=0; end
	2'b11: begin Q<=~Q; Qbar<=~Qbar; end
	endcase
	end
endmodule

Lab6/COUNTER.v
module COUNTERMOD6(
output Qa,
output Qb,
output Qc,
input CLK,
input RST
);
wire J1,J2,J3,BLANK1,BLANK2;
JKFF F1(Qa,BLANK1,1'b1,1'b1,RST,CLK);
JKFF F2(Qb,BLANK2,J1,Qa,RST,CLK);
JKFF F3(Qc,J3,J2,Qa,RST,CLK);
and A0(J1,Qa,J3);
and A1(J2,Qb,Qa);
endmodule

Lab6/DUT.v
module COUNTER_TEST();
wire Qa,Qb,Qc;
reg CLK,RST;
COUNTERMOD6 C1(Qa,Qb,Qc,CLK,RST);
always #10 CLK=~CLK;
initial begin
$dumpfile("dump.vcd");
$dumpvars(0, COUNTER_TEST);
RST=1;CLK=0;#20;
RST=0;#20;
#600
$finish;
end
endmodule

Lab6/dump.vcd
$date
	Sun Sep 21 20:07:53 2025
$end
$version
	Icarus Verilog
$end
$timescale
	1s
$end
$scope module COUNTER_TEST $end
$var wire 1 ! Qc $end
$var wire 1 " Qb $end
$var wire 1 # Qa $end
$var reg 1 $ CLK $end
$var reg 1 % RST $end
$scope module C1 $end
$var wire 1 $ CLK $end
$var wire 1 & J1 $end
$var wire 1 ' J2 $end
$var wire 1 % RST $end
$var wire 1 ! Qc $end
$var wire 1 " Qb $end
$var wire 1 # Qa $end
$var wire 1 ( J3 $end
$var wire 1 ) BLANK2 $end
$var wire 1 * BLANK1 $end
$scope module F1 $end
$var wire 1 $ CLK $end
$var wire 1 + J $end
$var wire 1 , K $end
$var wire 1 % RST $end
$var reg 1 # Q $end
$var reg 1 * Qbar $end
$upscope $end
$scope module F2 $end
$var wire 1 $ CLK $end
$var wire 1 & J $end
$var wire 1 # K $end
$var wire 1 % RST $end
$var reg 1 " Q $end
$var reg 1 ) Qbar $end
$upscope $end
$scope module F3 $end
$var wire 1 $ CLK $end
$var wire 1 ' J $end
$var wire 1 # K $end
$var wire 1 % RST $end
$var reg 1 ! Q $end
$var reg 1 ( Qbar $end
$upscope $end
$upscope $end
$upscope $end
$enddefinitions $end
$comment Show the parameter values. $end
$dumpall
$end
#0
$dumpvars
1,
1+
x*
x)
x(
0'
0&
1%
0$
0#
0"
0!
$end
#10
1*
1)
1(
1$
#20
0$
0%
#30
1&
0*
1#
1$
#40
0$
#50
0&
1*
0#
0)
1"
1$
#60
0$
#70
1'
1&
0*
1#
1$
#80
0$
#90
0'
0&
1*
0#
1)
0"
0(
1!
1$
#100
0$
#110
0*
1#
1$
#120
0$
#130
1*
0#
1(
0!
1$
#140
0$
#150
1&
0*
1#
1$
#160
0$
#170
0&
1*
0#
0)
1"
1$
#180
0$
#190
1'
1&
0*
1#
1$
#200
0$
#210
0'
0&
1*
0#
1)
0"
0(
1!
1$
#220
0$
#230
0*
1#
1$
#240
0$
#250
1*
0#
1(
0!
1$
#260
0$
#270
1&
0*
1#
1$
#280
0$
#290
0&
1*
0#
0)
1"
1$
#300
0$
#310
1'
1&
0*
1#
1$
#320
0$
#330
0'
0&
1*
0#
1)
0"
0(
1!
1$
#340
0$
#350
0*
1#
1$
#360
0$
#370
1*
0#
1(
0!
1$
#380
0$
#390
1&
0*
1#
1$
#400
0$
#410
0&
1*
0#
0)
1"
1$
#420
0$
#430
1'
1&
0*
1#
1$
#440
0$
#450
0'
0&
1*
0#
1)
0"
0(
1!
1$
#460
0$
#470
0*
1#
1$
#480
0$
#490
1*
0#
1(
0!
1$
#500
0$
#510
1&
0*
1#
1$
#520
0$
#530
0&
1*
0#
0)
1"
1$
#540
0$
#550
1'
1&
0*
1#
1$
#560
0$
#570
0'
0&
1*
0#
1)
0"
0(
1!
1$
#580
0$
#590
0*
1#
1$
#600
0$
#610
1*
0#
1(
0!
1$
#620
0$
#630
1&
0*
1#
1$
